README.md
setup.py
opaque/__init__.py
opaque/cli.py
opaque.egg-info/PKG-INFO
opaque.egg-info/SOURCES.txt
opaque.egg-info/dependency_links.txt
opaque.egg-info/requires.txt
opaque.egg-info/top_level.txt