Metadata-Version: 2.2
Name: opaque
Version: 1.0.0
Summary: python libopaque wrapper
Home-page: https://github.com/stef/libopaque
Author: Stefan Marsiske
Author-email: pyopaque@ctrlc.hu
License: GPLv3
Keywords: cryptography API libopaque OPAQUE PAKE AKE key-exchange
Classifier: Development Status :: 4 - Beta
Classifier: License :: OSI Approved :: GNU Lesser General Public License v3 or later (LGPLv3+)
Classifier: Topic :: Security :: Cryptography
Classifier: Topic :: Security
Requires: libsodium
Requires-Dist: pysodium
Dynamic: author
Dynamic: author-email
Dynamic: classifier
Dynamic: description
Dynamic: description-content-type
Dynamic: home-page
Dynamic: keywords
Dynamic: license
Dynamic: requires
Dynamic: requires-dist
Dynamic: summary
